ixpepy/__init__.py
ixpepy/_version.py
ixpepy/ixpeOGIPSpectrumLike.py
ixpepy/likelihood.py
ixpepy/data/toy_point_source_du1_pha1.fits
ixpepy/data/toy_point_source_du1_pha1q.fits
ixpepy/data/toy_point_source_du1_pha1u.fits
ixpepy/data/toy_point_source_du2_pha1.fits
ixpepy/data/toy_point_source_du2_pha1q.fits
ixpepy/data/toy_point_source_du2_pha1u.fits
ixpepy/data/toy_point_source_du3_pha1.fits
ixpepy/data/toy_point_source_du3_pha1q.fits
ixpepy/data/toy_point_source_du3_pha1u.fits
ixpepy-1.0.1.dist-info/licenses/LICENSE
ixpepy-1.0.1.dist-info/METADATA
ixpepy-1.0.1.dist-info/WHEEL
ixpepy-1.0.1.dist-info/top_level.txt
ixpepy-1.0.1.dist-info/RECORD
